Workbook

Sheet Instructions
A1: MS Excel Practical Exam
A2: Total Questions: 30
A3: Difficulty Level: Medium
A4: Syllabus: Formulas, Logical Functions, Lookups, INDEX-MATCH, Pivot Tables & Charts, Data Analysis
A5: Attempt all questions using appropriate Excel tools/functions.

Sheet Sales_Data
A1: Order_ID | B1: Region | C1: Salesperson | D1: Product | E1: Quantity | F1: Unit_Price | G1: Sales_Date | H1: Total sales | I1: gst | J1: Total amount | K1: Qty_status | L1: Month | M1: category | N1: Sales_p | R1: Product | S1: Total_sales
A2: 301 | B2: North | C2: Amit | D2: Laptop | E2: 2 | F2: 45000 | G2: 05-01-2025 | H2: =(E2*F2) -> 90000 | I2: =VLOOKUP(D2,Product_Master!$A$2:$C$4,3,0)/100*H2 -> 16200 | J2: =H2+I2 -> 106200 | K2: =IF(E2>3,"High",IF(E2<=3,"low")) -> low | L2: =TEXT(G2,"mmmm") -> January | M2: INDEX(A2:L7,MATCH(Sales_Data!D2,Product_Master!B2:B4,2)) | N2: =LEFT(C2,2) -> Am | R2: Laptop | S2: 225000
A3: 302 | B3: South | C3: Riya | D3: Mobile | E3: 5 | F3: 15000 | G3: 07-01-2025 | H3: =(E3*F3) -> 75000 | I3: =VLOOKUP(D3,Product_Master!$A$2:$C$4,3,0)/100*H3 -> 9000 | J3: =H3+I3 -> 84000 | K3: =IF(E3>3,"High",IF(E3<=3,"low")) -> High | L3: =TEXT(G3,"mmmm") -> January | M3: =INDEX(A3:L8,MATCH(Sales_Data!D3,Sales_Data!D3:D8,0),4) -> Mobile | N3: =LEFT(C3,2) -> Ri | R3: Mobile | S3: 135000
A4: 303 | B4: East | C4: Kunal | D4: Tablet | E4: 3 | F4: 18000 | G4: 10-01-2025 | H4: =(E4*F4) -> 54000 | I4: =VLOOKUP(D4,Product_Master!$A$2:$C$4,3,0)/100*H4 -> 6480 | J4: =H4+I4 -> 60480 | K4: =IF(E4>3,"High",IF(E4<=3,"low")) -> low | L4: =TEXT(G4,"mmmm") -> January | M4: =INDEX(A4:L9,MATCH(Sales_Data!D4,Sales_Data!D4:D9,0),4) -> Tablet | N4: =LEFT(C4,2) -> Ku | R4: Tablet | S4: 54000
A5: 304 | B5: West | C5: Neha | D5: Laptop | E5: 1 | F5: 45000 | G5: 12-01-2025 | H5: =(E5*F5) -> 45000 | I5: =VLOOKUP(D5,Product_Master!$A$2:$C$4,3,0)/100*H5 -> 8100 | J5: =H5+I5 -> 53100 | K5: =IF(E5>3,"High",IF(E5<=3,"low")) -> low | L5: =TEXT(G5,"mmmm") -> January | M5: =INDEX(A5:L10,MATCH(Sales_Data!D5,Sales_Data!D5:D10,0),4) -> Laptop | N5: =LEFT(C5,2) -> Ne | R5: Grand Total | S5: 414000
A6: 305 | B6: North | C6: Amit | D6: Mobile | E6: 4 | F6: 15000 | G6: 15-01-2025 | H6: =(E6*F6) -> 60000 | I6: =VLOOKUP(D6,Product_Master!$A$2:$C$4,3,0)/100*H6 -> 7200 | J6: =H6+I6 -> 67200 | K6: =IF(E6>3,"High",IF(E6<=3,"low")) -> High | L6: =TEXT(G6,"mmmm") -> January | M6: =INDEX(A6:L11,MATCH(Sales_Data!D6,Sales_Data!D6:D11,0),4) -> Mobile | N6: =LEFT(C6,2) -> Am
A7: 306 | B7: South | C7: Riya | D7: Laptop | E7: 2 | F7: 45000 | G7: 18-01-2025 | H7: =(E7*F7) -> 90000 | I7: =VLOOKUP(D7,Product_Master!$A$2:$C$4,3,0)/100*H7 -> 16200 | J7: =H7+I7 -> 106200 | K7: =IF(E7>3,"High",IF(E7<=3,"low")) -> low | L7: =TEXT(G7,"mmmm") -> January | M7: =INDEX(A7:L12,MATCH(Sales_Data!D7,Sales_Data!D7:D12,0),4) -> Laptop | N7: =LEFT(C7,2) -> Ri
R8: Regin | S8: Total_sales
I9: Grand total | J9: =SUM(J2:J7) -> 477180 | R9: South | S9: 165000
I10: Total orders | J10: =COUNTA(A2:A7) -> 6 | R10: West | S10: 45000
R11: East | S11: 54000
R12: North | S12: 150000
B13: North sales | C13: =SUMIF(Sales_Data!$B$2:$B$7,Sales_Data!B2,Sales_Data!$J$2:$J$7) -> 173400 | E13: Max amount | F13: =MAX(J2:J7) -> 106200 | R13: Grand Total | S13: 414000
B14: South sales | C14: =SUMIF(Sales_Data!$B$2:$B$7,Sales_Data!B3,Sales_Data!$J$2:$J$7) -> 190200 | E14: Min amount | F14: =MIN(J2:J7) -> 53100
B15: West sales | C15: =SUMIF(Sales_Data!$B$2:$B$7,Sales_Data!B4,Sales_Data!$J$2:$J$7) -> 60480
B16: east sales | C16: =SUMIF(Sales_Data!$B$2:$B$7,Sales_Data!B5,Sales_Data!$J$2:$J$7) -> 53100
N18: filter
A19: {=_xlfn._xlws.SORT(A1:L7,10,-1)} -> Order_ID | B19: Region | C19: Salesperson | D19: Product | E19: Quantity | F19: Unit_Price | G19: Sales_Date | H19: Total sales | I19: gst | J19: Total amount | K19: Qty_status | L19: Month | N19: {=_xlfn._xlws.FILTER(A2:L7,(D2:D7="Laptop")*(E2:E7>1),"")} -> 301 | O19: North | P19: Amit | Q19: Laptop | R19: 2 | S19: 45000 | T19: 05-01-2025 | U19: 90000 | V19: 16200 | W19: 106200 | X19: low | Y19: January
A20: 301 | B20: North | C20: Amit | D20: Laptop | E20: 2 | F20: 45000 | G20: 05-01-2025 | H20: 90000 | I20: 16200 | J20: 106200 | K20: low | L20: January | N20: 306 | O20: South | P20: Riya | Q20: Laptop | R20: 2 | S20: 45000 | T20: 18-01-2025 | U20: 90000 | V20: 16200 | W20: 106200 | X20: low | Y20: January
A21: 306 | B21: South | C21: Riya | D21: Laptop | E21: 2 | F21: 45000 | G21: 18-01-2025 | H21: 90000 | I21: 16200 | J21: 106200 | K21: low | L21: January
A22: 302 | B22: South | C22: Riya | D22: Mobile | E22: 5 | F22: 15000 | G22: 07-01-2025 | H22: 75000 | I22: 9000 | J22: 84000 | K22: High | L22: January | N22: countifs | O22: =COUNTIFS(Sales_Data!B2:B7,"north",D2:D7,"laptop") -> 1
A23: 305 | B23: North | C23: Amit | D23: Mobile | E23: 4 | F23: 15000 | G23: 15-01-2025 | H23: 60000 | I23: 7200 | J23: 67200 | K23: High | L23: January
A24: 303 | B24: East | C24: Kunal | D24: Tablet | E24: 3 | F24: 18000 | G24: 10-01-2025 | H24: 54000 | I24: 6480 | J24: 60480 | K24: low | L24: January
A25: 304 | B25: West | C25: Neha | D25: Laptop | E25: 1 | F25: 45000 | G25: 12-01-2025 | H25: 45000 | I25: 8100 | J25: 53100 | K25: low | L25: January

Sheet Product_Master
A1: Product | B1: Category | C1: GST_%
A2: Laptop | B2: Electronics | C2: 18
A3: Mobile | B3: Electronics | C3: 12
A4: Tablet | B4: Electronics | C4: 12

Sheet Student_Marks
A1: Student_ID | B1: Name | C1: Maths | D1: Statistics | E1: Excel | F1: Attendance_% | G1: Avg marks | H1: Eligiblity | I1: Concate
A2: 1 | B2: Rahul | C2: 78 | D2: 82 | E2: 85 | F2: 92 | G2: =ROUND(AVERAGE(C2:E2),2) -> 81.67 | H2: =IF(F2>85,"Eligible","Not Eligible") -> Eligible | I2: =_xlfn.CONCAT(Student_Marks!A2,"_",Student_Marks!B2) -> 1_Rahul
A3: 2 | B3: Sneha | C3: 88 | D3: 91 | E3: 90 | F3: 96 | G3: =ROUND(AVERAGE(C3:E3),2) -> 89.67 | H3: =IF(F3>85,"Eligible","Not Eligible") -> Eligible | I3: =_xlfn.CONCAT(Student_Marks!A3,"_",Student_Marks!B3) -> 2_Sneha
A4: 3 | B4: Arjun | C4: 65 | D4: 70 | E4: 72 | F4: 85 | G4: =ROUND(AVERAGE(C4:E4),2) -> 69 | H4: =IF(F4>85,"Eligible","Not Eligible") -> Not Eligible | I4: =_xlfn.CONCAT(Student_Marks!A4,"_",Student_Marks!B4) -> 3_Arjun
A5: 4 | B5: Pooja | C5: 92 | D5: 89 | E5: 94 | F5: 98 | G5: =ROUND(AVERAGE(C5:E5),2) -> 91.67 | H5: =IF(F5>85,"Eligible","Not Eligible") -> Eligible | I5: =_xlfn.CONCAT(Student_Marks!A5,"_",Student_Marks!B5) -> 4_Pooja
A6: 5 | B6: Vikas | C6: 55 | D6: 60 | E6: 58 | F6: 80 | G6: =ROUND(AVERAGE(C6:E6),2) -> 57.67 | H6: =IF(F6>85,"Eligible","Not Eligible") -> Not Eligible | I6: =_xlfn.CONCAT(Student_Marks!A6,"_",Student_Marks!B6) -> 5_Vikas
F9: Topper | G9: =_xlfn.XLOOKUP(MAX(G2:G6),G2:G6,B2:B6) -> Pooja
F10: Total regular students | G10: =COUNTIF(F2:F6,">90") -> 3
F11: Median | G11: =MEDIAN(D2:D6) -> 82
F12: Standard dev | G12: =_xlfn.STDEV.S(Student_Marks!E2:E6) -> 14.737707

Sheet Questions
A1: 1. Calculate Total Sales for each order (Quantity × Unit_Price). | J1: 2
A2: 2. Calculate GST Amount using VLOOKUP from Product_Master. | J2: 2
A3: 3. Find Final Amount payable (Total Sales + GST). | J3: 2
A4: 4. Find Grand Total of Final Amount. | J4: 2
A5: 5. Count total number of orders using COUNTA. | J5: 2
A6: 6. Find Region-wise total sales using SUMIF. | J6: 2
A7: 7. Use IF to classify Quantity as High (>3) or Low (<=3). | J7: 2
A8: 8. Find the maximum and minimum Final Amount. | J8: 2
A9: 9. Extract month name from Sales_Date. | J9: 2
A10: 10. Sort Sales_Data by Final Amount (Descending). | J10: 2
A11: 11. Use INDEX-MATCH to fetch Product Category. | J11: 2
A12: 12. Calculate average marks of each student. | J12: 2
... A30: 30. Protect the Student_Marks sheet. | J30: 2
J32: =SUM(J1:J30) -> 60
